{
  "job_description": "About the job\nWe are seeking a curious, dynamic and passionate individual to join our team as a Lead Solution Architect & AI / Data Innovator. This role will be responsible for designing, implementing, and delivering RAG (Real-time Adaptive Generation) and AI agent solutions utilizing enterprise data that not only solve business challenges but also drive significant value for our clients. You will be trusted for explaining the value proposition and technical differentiators of our products to customers, understanding their requirements, showing insightful demos, running successful POC\u2019s (proof of concepts) and deployments and helping to drive revenue for the company.\n\nAbout Us:\n\nWe are changing the game on how Enterprise AI-powered applications are built and offered to fortune 5000 global enterprises. We are combining both cutting-edge advancements in machine learning and cloud systems to highly-researched, high-value products for the enterprise. \n\nJob Summary:\n\nAs the Lead Solution Architect & AI Innovator, you will work closely with cross-functional teams to understand client needs and develop tailored AI-driven solutions. You will be responsible for building robust RAG and AI agent platforms using cutting-edge technologies.\n\n\n\nKey Responsibilities:\n\nWork collaboratively with business stakeholders to identify opportunities where advanced AI can add significant value.\nCollaborate closely with product development teams to design scalable solutions that meet the needs of our clients.\nDevelop and maintain RAG models that enable real-time adaptive generation of content based on user queries, preferences, and historical data.\nDesign and implement AI agents for tasks such as customer service, sales support, and strategic planning.\nLead Proof of Concept efforts, ensuring timely delivery and adherence to quality standards.\nContinuously improve existing solutions by incorporating new technologies and methodologies.\nContribute to the development of internal documentation and guidelines on RAG and AI agent best practices.\n\n\nRequirements:\n\nBachelor\u2019s degree in Computer Science, Engineering, or a related field. Advanced degrees are preferred.\n7+ years of experience as a Solution Architect/Technical Consultant in the IT industry with a focus on Data and AI solutions.\nExceptional understanding of enterprise applications, data systems, SAAS, Networking and Authentication techniques. \nStrong understanding of compliance, privacy and security of data\nProven track record of successfully leading enterprise complex projects from planning through implementation and beyond.\nDemonstrated experience with Enterprise Data Catalog Products or Enterprise Data Observability platforms.\nStrong understanding of RAG models and machine learning principles is essential.\nExperience in designing, developing, and implementing AI agents for business applications.\nSolid experience working with Linux, Python, JSON, YAML is a must. \nExcellent communication skills; ability to articulate technical ideas clearly to non-technical stakeholders.\nAbility to work well under pressure while meeting tight deadlines and managing multiple projects simultaneously.\n\n\nWhat We Offer:\n\nA dynamic and fast-paced environment where you can make a meaningful impact.\nOpportunities for professional growth and development through innovative solutions.\nCompetitive salary package, comprehensive benefits, stock options, and more.\nAn inclusive culture that values diversity and encourages collaboration across teams.\nApplication Instructions:\n\nPlease submit your resume along with a cover letter detailing how you meet the requirements of this role. Please make sure to mention \u201cLead Solution Architect & AI Innovator\u201d in the subject line of the email. We appreciate your interest and look forward to reviewing your application.",
  "raw_analysis": "### Detailed Analysis and Recommendations for Tailoring the Resume\n\n#### 1. Key Requirements and Qualifications from the Job Description\n- Bachelor's degree in Computer Science, Engineering, or related field; advanced degrees preferred.\n- 7+ years of experience as a Solution Architect/Technical Consultant in IT with a focus on Data and AI solutions.\n- Proven track record of leading complex enterprise projects.\n- Experience with Enterprise Data Catalog Products or Enterprise Data Observability platforms.\n- Strong understanding of RAG models and machine learning principles.\n- Experience in designing, developing, and implementing AI agents for business applications.\n\n#### 2. Technical Skills and Tools Required\n- Proficiency in Linux, Python, JSON, YAML.\n- Understanding of enterprise applications, data systems, SAAS, Networking, and Authentication techniques.\n- Knowledge of compliance, privacy, and security of data.\n\n#### 3. Soft Skills Emphasized\n- Excellent communication skills for articulating technical ideas to non-technical stakeholders.\n- Ability to work well under pressure, meet tight deadlines, and manage multiple projects simultaneously.\n\n#### 4. Industry-Specific Terminology and Keywords\n- RAG (Real-time Adaptive Generation)\n- AI agent solutions\n- Enterprise Data Catalog\n- Data Observability\n- Machine Learning\n- Proof of Concepts (POC)\n- Cross-functional teams\n\n#### 5. Company Values and Culture Indicators\n- Dynamic and fast-paced environment.\n- Opportunities for professional growth and development.\n- Inclusive culture that values diversity and encourages collaboration.\n\n#### 6. Specific Modifications to Recommend for Each Resume Section\n\n**Personal Details:**\n- Ensure contact information is up-to-date and includes professional profiles like LinkedIn.\n- Mention \"Lead Solution Architect & AI Innovator\" in the email subject line as per application instructions.\n\n**Professional Summary:**\n- Highlight experience in leading complex enterprise projects and developing AI-driven solutions.\n- Mention a strong track record in using RAG models and AI agents.\n- Emphasize the ability to communicate complex technical concepts to non-technical stakeholders.\n\n**Technical Skills:**\n- List Linux, Python, JSON, YAML prominently.\n- Include skills related to enterprise applications, data systems, SAAS, Networking, and Authentication.\n- Add any experience with Enterprise Data Catalog Products or Data Observability platforms.\n\n**Experience:**\n- Focus on roles that involved leading AI and data-driven projects.\n- Highlight achievements in designing and implementing AI agent solutions.\n- Include specific examples of successful POCs and deployments.\n\n**Certifications:**\n- List any relevant certifications in AI, data science, or solution architecture.\n- If applicable, mention certifications related to compliance, privacy, and security of data.\n\n**Education:**\n- Ensure the degree in Computer Science, Engineering, or related field is clearly listed.\n- Mention any advanced degrees or ongoing education relevant to AI and data solutions.\n\n#### 7. Priority Ranking of Changes\n\n- **High Importance:**\n  - Update Professional Summary to align with key responsibilities and soft skills.\n  - Highlight relevant Technical Skills, especially Linux, Python, JSON, YAML.\n  - Emphasize Experience in leading AI-driven projects and successful POCs.\n\n- **Medium Importance:**\n  - Ensure Education section reflects relevant degrees.\n  - Include Certifications that bolster qualifications for this role.\n\n- **Low Importance:**\n  - Adjust Personal Details to ensure all contact information is current and professional.\n  - Tailor the format and style of the resume to ensure clarity and readability, using LaTeX commands effectively.\n\nBy implementing these recommendations, the resume will be better aligned with the job description, increasing the likelihood of capturing the attention of hiring managers for the Lead Solution Architect & AI Innovator position.",
  "structured_recommendations": {
    "key_requirements": [
      "Bachelor's degree in Computer Science, Engineering, or related field; advanced degrees preferred.",
      "7+ years of experience as a Solution Architect/Technical Consultant in IT with a focus on Data and AI solutions.",
      "Proven track record of leading complex enterprise projects.",
      "Experience with Enterprise Data Catalog Products or Enterprise Data Observability platforms.",
      "Strong understanding of RAG models and machine learning principles.",
      "Experience in designing, developing, and implementing AI agents for business applications."
    ],
    "technical_skills": [
      "Linux",
      "Python",
      "JSON",
      "YAML",
      "Enterprise applications",
      "Data systems",
      "SAAS",
      "Networking",
      "Authentication techniques",
      "Compliance, privacy, and security of data"
    ],
    "soft_skills": [
      "Excellent communication skills for articulating technical ideas to non-technical stakeholders.",
      "Ability to work well under pressure, meet tight deadlines, and manage multiple projects simultaneously."
    ],
    "keywords": [
      "RAG (Real-time Adaptive Generation)",
      "AI agent solutions",
      "Enterprise Data Catalog",
      "Data Observability",
      "Machine Learning",
      "Proof of Concepts (POC)",
      "Cross-functional teams"
    ],
    "section_recommendations": {
      "Personal Details": [
        "Ensure contact information is up-to-date and includes professional profiles like LinkedIn.",
        "Mention 'Lead Solution Architect & AI Innovator' in the email subject line as per application instructions."
      ],
      "Professional Summary": [
        "Highlight experience in leading complex enterprise projects and developing AI-driven solutions.",
        "Mention a strong track record in using RAG models and AI agents.",
        "Emphasize the ability to communicate complex technical concepts to non-technical stakeholders."
      ],
      "Technical Skills": [
        "List Linux, Python, JSON, YAML prominently.",
        "Include skills related to enterprise applications, data systems, SAAS, Networking, and Authentication.",
        "Add any experience with Enterprise Data Catalog Products or Data Observability platforms."
      ],
      "Experience": [
        "Focus on roles that involved leading AI and data-driven projects.",
        "Highlight achievements in designing and implementing AI agent solutions.",
        "Include specific examples of successful POCs and deployments."
      ],
      "Certifications": [
        "List any relevant certifications in AI, data science, or solution architecture.",
        "If applicable, mention certifications related to compliance, privacy, and security of data."
      ],
      "Education": [
        "Ensure the degree in Computer Science, Engineering, or related field is clearly listed.",
        "Mention any advanced degrees or ongoing education relevant to AI and data solutions."
      ]
    },
    "prioritized_changes": [
      {
        "priority": "High Importance",
        "changes": [
          "Update Professional Summary to align with key responsibilities and soft skills.",
          "Highlight relevant Technical Skills, especially Linux, Python, JSON, YAML.",
          "Emphasize Experience in leading AI-driven projects and successful POCs."
        ]
      },
      {
        "priority": "Medium Importance",
        "changes": [
          "Ensure Education section reflects relevant degrees.",
          "Include Certifications that bolster qualifications for this role."
        ]
      },
      {
        "priority": "Low Importance",
        "changes": [
          "Adjust Personal Details to ensure all contact information is current and professional.",
          "Tailor the format and style of the resume to ensure clarity and readability, using LaTeX commands effectively."
        ]
      }
    ]
  }
}