{
  "raw_latex_analysis": {
    "document_class": {
      "name": "article",
      "options": "letterpaper,10pt"
    },
    "packages": [
      {
        "name": "latexsym",
        "options": ""
      },
      {
        "name": "fullpage",
        "options": "empty"
      },
      {
        "name": "titlesec",
        "options": ""
      },
      {
        "name": "marvosym",
        "options": ""
      },
      {
        "name": "color",
        "options": "usenames,dvipsnames"
      },
      {
        "name": "verbatim",
        "options": ""
      },
      {
        "name": "enumitem",
        "options": ""
      },
      {
        "name": "hyperref",
        "options": "hidelinks"
      },
      {
        "name": "fancyhdr",
        "options": ""
      },
      {
        "name": "babel",
        "options": "english"
      },
      {
        "name": "tabularx",
        "options": ""
      },
      {
        "name": "geometry",
        "options": ""
      }
    ],
    "commands": [
      "\\newcommand{\\resumeItem}[1]{\n  \\item\\small{\n    {#1 \\vspace{-1.5pt}",
      "\\newcommand{\\resumeSubheading}[4]{\n  \\vspace{-2pt}",
      "\\newcommand{\\resumeProjectHeading}[2]{\n    \\item\n    \\begin{tabular*}",
      "\\newcommand{\\resumeSubHeadingListStart}{\\begin{itemize}",
      "\\newcommand{\\resumeSubHeadingListEnd}{\\end{itemize}",
      "\\newcommand{\\resumeItemListStart}{\\begin{itemize}",
      "\\newcommand{\\resumeItemListEnd}{\\end{itemize}"
    ],
    "sections": {
      "PROFESSIONAL SUMMARY": "Results-driven MLOps Engineer with a Master\u2019s in Data Science, delivering 40\\% faster ML deployments via Kubernetes on AWS and 30\\% cost savings through cloud optimization. Led cross-functional teams to improve model accuracy by 15\\% and mentored engineers, boosting productivity by 20\\%. Passionate about fostering innovation, inclusivity, and continuous learning.\n\n%-----------Technical Skills-----------",
      "TECHNICAL SKILLS": "\\resumeSubHeadingListStart\n\\resumeItem{\n{\\fontsize{9}{11}\\selectfont\n\\begin{tabularx}{\\textwidth}{@{} l X @{}}\n\\textbf{Programming Languages:} & Python, Java, C#, SQL \\\\\n\\textbf{Cloud Platforms:} & AWS, Azure, Google Cloud (Vertex AI, BigQuery, Dataflow), GCP \\\\\n\\textbf{Data Processing \\& Analytics:} & Spark (MLlib, Spark SQL), Hadoop, Pandas, Numpy, Scipy \\\\\n\\textbf{Machine Learning:} & Scikit-learn, TensorFlow, PyTorch, Gradient Boosting, Random Forest \\\\\n\\textbf{MLOps Tools:} & MLflow, Kubeflow, SageMaker \\\\\n\\textbf{Infrastructure as Code:} & Terraform, CloudFormation \\\\\n\\textbf{CI/CD Pipelines:} & Jenkins, GitLab CI, GitHub Actions \\\\\n\\textbf{Containerization:} & Docker, Kubernetes \\\\\n\\textbf{Project Management:} & Agile (Scrum, Kanban), Cross-Functional Collaboration \\\\\n\\end{tabularx}\n}\n}\n\\resumeSubHeadingListEnd\n\n\\vspace{-4.5mm}\n\n%-----------EXPERIENCE-----------",
      "EXPERIENCE": "\\resumeSubHeadingListStart\n\n%-----------Katbotz EXPERIENCE-----------\n\\resumeSubheading\n{Katbotz}{\\textit{September 2024 -- Present}}\n{Senior MLOps Engineer}{New York City, NY}\n\\resumeItemListStart\n    \\resumeItem{Designed and deployed Kubernetes clusters on AWS to containerize ML models, reducing deployment time by 40\\% and enabling scalable inference.}\n    \\resumeItem{Orchestrated CI/CD pipelines using Jenkins to automate model retraining, improving accuracy by 15\\% and cutting downtime by 30\\%.}\n    \\resumeItem{Collaborated with data scientists to implement MLflow for model validation, ensuring production-ready models met 99\\% accuracy thresholds.}\n    \\resumeItem{Led cross-functional teams to build feature engineering pipelines on Spark, accelerating data preprocessing by 40\\% for real-time analytics.}\n    \\resumeItem{Mentored 3 junior engineers on MLOps best practices, enhancing team productivity by 20\\% through knowledge-sharing initiatives.}\n\\resumeItemListEnd\n\n%-----------Dark Matter Technologies EXPERIENCE-----------\n\\resumeSubheading\n{Dark Matter Technologies}{\\textit{June 2023 -- December 2023}}\n{AI/ML Ops Engineer}{Jacksonville, FL}\n\\resumeItemListStart\n    \\resumeItem{Optimized Azure Databricks workflows using Terraform, reducing cloud costs by 25\\% while maintaining 99.5\\% uptime for ML models.}\n    \\resumeItem{Streamlined model lifecycle management with SageMaker, cutting retraining cycles from 12 to 4 hours and boosting ROI by 22\\%.}\n    \\resumeItem{Implemented Docker containers for edge devices, enabling offline inference and reducing latency by 35\\% in distributed networks.}\n    \\resumeItem{Championed Agile Scrum practices, leading a team of 5 to deliver 8 ML-driven features in 6 sprints, aligning with product goals.}\n    \\resumeItem{Synthesized performance dashboards for executives using Tableau, translating model efficacy into actionable insights for \\$500K infrastructure upgrades.}\n\\resumeItemListEnd\n\n%-----------Digital Pass EXPERIENCE-----------\n\\resumeSubheading\n{Digital Pass}{\\textit{June 2020 -- June 2022}}\n{Machine Learning Engineer}{Indore, India}\n\\resumeItemListStart\n    \\resumeItem{Engineered GCP-based MLOps pipelines to automate capacity planning, achieving 30\\% cost savings via predictive bandwidth allocation.}\n    \\resumeItem{Transformed raw IoT data into network health indicators using PySpark, reducing packet loss by 21\\% for 2M+ devices.}\n    \\resumeItem{Implemented feature engineering pipelines for XGBoost models, improving churn prediction accuracy by 25\\% (AUC-ROC: 0.92).}\n    \\resumeItem{Collaborated with DevOps to deploy monitoring tools, cutting incident response time by 40\\% through real-time anomaly detection.}\n    \\resumeItem{Led training sessions on Kubeflow for data engineers, fostering a culture of continuous learning and tool adoption.}\n\\resumeItemListEnd\n\n%-----------SK Enterprises EXPERIENCE-----------\n\\resumeSubheading\n{SK Enterprises}{\\textit{January 2019 -- June 2020}}\n{Data Scientist}{Indore, India}\n\\resumeItemListStart\n    \\resumeItem{Maximized data utility via PySpark pipelines, cleaning 10TB+ daily customer data to enable 9\\% ARPU growth through targeted offerings.}\n    \\resumeItem{Formulated k-means segmentation models, informing personalized service plans that increased customer retention by 12\\%.}\n\\resumeItemListEnd\n\n\\resumeSubHeadingListEnd\n\n%-----------Certifications-----------",
      "CERTIFICATIONS": "\\resumeSubHeadingListStart\n    \\resumeItem{AWS Certified Data Engineer Associate (DEA-C01)\\hfill \\textit{April 2024 -- April 2027}}\n\\resumeSubHeadingListEnd\n\n%-----------Education-----------",
      "EDUCATION": "\\resumeSubHeadingListStart\n    \\resumeSubheading\n      {Drexel University}{\\textit{Philadelphia, PA}}\n      {Master of Science in Data Science}{}\n    \\resumeSubheading\n      {Rajiv Gandhi Proudyogiki Vishwavidyalaya}{\\textit{Bhopal, India}}\n      {Bachelor of Technology in Computer Science and Engineering}{}\n\\resumeSubHeadingListEnd"
    },
    "environments": [
      {
        "name": "tabular*",
        "content": "{0.97\\textwidth}[t]{l@{\\extracolsep{\\fill}}r}\n      \\textbf{#1} & #2 \\\\\n      \\textit{\\small#3} & \\t..."
      },
      {
        "name": "tabular*",
        "content": "{0.97\\textwidth}{l@{\\extracolsep{\\fill}}r}\n      \\small#1 & #2 \\\\"
      },
      {
        "name": "itemize",
        "content": "[leftmargin=0.15in, label={}]}\n\\newcommand{\\resumeSubHeadingListEnd}{"
      },
      {
        "name": "itemize",
        "content": "[leftmargin=0.15in]}\n\\newcommand{\\resumeItemListEnd}{"
      },
      {
        "name": "document",
        "content": "\\begin{center}\n    \\textbf{\\Huge \\scshape Rishabh Sharma}\n\\end{center}\n\\begin{center}\n    \\small\n   ..."
      }
    ]
  },
  "llm_analysis": "### Comprehensive Analysis of the LaTeX Resume\n\n#### 1. Overall Structure of the Resume\nThe resume is structured using the `article` document class, which is a common choice for creating simple documents without chapters. The document is organized into several sections, each representing a different aspect of the candidate's professional profile. The structure is designed to be concise and easy to read, with a focus on key information.\n\n#### 2. Sections Identified and Their Purpose\n- **Personal Details**: Located at the top of the document, this section includes the candidate's name, contact information, and links to professional profiles (LinkedIn, personal website, GitHub).\n- **Professional Summary**: Provides a brief overview of the candidate's career achievements and professional focus.\n- **Technical Skills**: Lists the candidate's technical proficiencies, categorized by type (e.g., Programming Languages, Cloud Platforms).\n- **Experience**: Details the candidate's work history, including job titles, companies, locations, and key responsibilities and achievements.\n- **Certifications**: Lists relevant professional certifications, including the certification name and validity period.\n- **Education**: Outlines the candidate's academic background, including degrees obtained and institutions attended.\n\n#### 3. LaTeX Commands and Environments Used\n- **Document Class**: `\\documentclass[letterpaper,10pt]{article}` sets the document type and font size.\n- **Packages**: Various packages are imported to enhance functionality and formatting (discussed in detail below).\n- **Sections**: Defined using `\\section{}` for major headings.\n- **Tabular Environment**: `tabularx` is used for aligning text in columns, particularly in the skills and experience sections.\n- **Itemize Environment**: Used for listing items, such as skills and job responsibilities.\n\n#### 4. Template Style and Formatting\n- **Margins**: Adjusted using the `geometry` package to provide more space for content.\n- **Font and Text Style**: The resume uses a mix of bold (`\\textbf{}`), italic (`\\textit{}`), and small caps (`\\scshape`) for emphasis and hierarchy.\n- **Section Formatting**: Customized using the `titlesec` package to control the appearance of section headings, including spacing and rules.\n- **Alignment**: The document uses `\\raggedright` and `\\raggedbottom` to control text alignment and spacing.\n\n#### 5. Package Imports and Their Purpose\n- **`latexsym`**: Provides additional symbols.\n- **`fullpage`**: Sets page margins to be smaller, allowing more content per page.\n- **`titlesec`**: Customizes section headings.\n- **`marvosym`**: Provides additional symbols, such as those used in contact information.\n- **`color`**: Allows the use of colors in the document.\n- **`verbatim`**: Facilitates the inclusion of verbatim text.\n- **`enumitem`**: Customizes list environments.\n- **`hyperref`**: Adds hyperlinks to the document, with `hidelinks` to prevent link coloring.\n- **`fancyhdr`**: Customizes headers and footers.\n- **`babel`**: Manages language-specific typographic rules.\n- **`tabularx`**: Provides a tabular environment with adjustable column widths.\n- **`geometry`**: Adjusts page margins.\n\n#### 6. Custom Commands and Their Function\n- **`\\resumeItem{}`**: Formats individual items in lists, reducing vertical space.\n- **`\\resumeSubheading{}`**: Formats subheadings for job titles and educational qualifications, aligning text in two columns.\n- **`\\resumeProjectHeading{}`**: Similar to `\\resumeSubheading`, but used for project descriptions.\n- **`\\resumeSubHeadingListStart` and `\\resumeSubHeadingListEnd`**: Begin and end a list of subheadings.\n- **`\\resumeItemListStart` and `\\resumeItemListEnd`**: Begin and end a list of items under a subheading.\n- **`\\renewcommand\\labelitemii{}`**: Customizes the bullet symbol for nested lists.\n\n### Conclusion\nThis LaTeX resume template is designed for clarity and conciseness, with a focus on presenting professional information in a structured manner. The use of custom commands and packages allows for a high degree of customization, making it easy to adapt the template for different users or preferences. The template's structure and formatting are optimized for readability and efficient use of space, making it suitable for professional applications.",
  "sections": [
    {
      "name": "Personal Details",
      "purpose": "Includes the candidate's name, contact information, and links to professional profiles."
    },
    {
      "name": "Professional Summary",
      "purpose": "Provides a brief overview of the candidate's career achievements and professional focus."
    },
    {
      "name": "Technical Skills",
      "purpose": "Lists the candidate's technical proficiencies, categorized by type."
    },
    {
      "name": "Experience",
      "purpose": "Details the candidate's work history, including job titles, companies, locations, and key responsibilities and achievements."
    },
    {
      "name": "Certifications",
      "purpose": "Lists relevant professional certifications, including the certification name and validity period."
    },
    {
      "name": "Education",
      "purpose": "Outlines the candidate's academic background, including degrees obtained and institutions attended."
    }
  ],
  "structure": [
    "Personal Details",
    "Professional Summary",
    "Technical Skills",
    "Experience",
    "Certifications",
    "Education"
  ],
  "recommendations": [
    "Consider adding a section for 'Projects' if applicable, to highlight specific work or contributions.",
    "Ensure that the contact information is up-to-date and includes all relevant links.",
    "Review the 'Professional Summary' to ensure it aligns with the job being applied for.",
    "Customize the 'Technical Skills' section to prioritize skills most relevant to the desired position.",
    "Use consistent formatting for dates and locations across the 'Experience' and 'Education' sections."
  ],
  "commands": [
    "\\documentclass[letterpaper,10pt]{article}",
    "\\section{}",
    "\\textbf{}",
    "\\textit{}",
    "\\scshape",
    "\\raggedright",
    "\\raggedbottom",
    "\\resumeItem{}",
    "\\resumeSubheading{}",
    "\\resumeProjectHeading{}",
    "\\resumeSubHeadingListStart",
    "\\resumeSubHeadingListEnd",
    "\\resumeItemListStart",
    "\\resumeItemListEnd",
    "\\renewcommand\\labelitemii{}"
  ]
}